LICENSE
MANIFEST.in
README.md
setup.py
motorcortex_robot_control_python.egg-info/PKG-INFO
motorcortex_robot_control_python.egg-info/SOURCES.txt
motorcortex_robot_control_python.egg-info/dependency_links.txt
motorcortex_robot_control_python.egg-info/requires.txt
motorcortex_robot_control_python.egg-info/top_level.txt
robot_control/__init__.py
robot_control/motionSL_hash.json
robot_control/motionSL_pb2.py
robot_control/motionSL_v1_hash.json
robot_control/motionSL_v1_pb2.py
robot_control/motion_program.py
robot_control/multirobot_command.py
robot_control/robot_command.py
robot_control/system_defs.py