Metadata-Version: 2.1
Name: motorcortex-robot-control-python
Version: 3.1.3
Summary: Python bindings for Motorcortex Robot Control
Home-page: https://www.motorcortex.io
Author: Alexey Zakharov
Author-email: info@vectioneer.com
License: MIT
License-File: LICENSE
Requires-Dist: motorcortex-python
